whosper/__init__.py
whosper/transcription.py
whosper-0.1.0.dist-info/licenses/LICENCE
whosper-0.1.0.dist-info/METADATA
whosper-0.1.0.dist-info/WHEEL
whosper-0.1.0.dist-info/top_level.txt
whosper-0.1.0.dist-info/RECORD
